hive_data_access/_internal/_index.cpython-313-darwin.so
hive_data_access/_internal/_enum.cpython-313-darwin.so
hive_data_access/_internal/__init__.py
hive_data_access/_internal/_description.cpython-313-darwin.so
hive_data_access/_internal/_reader.cpython-313-darwin.so
hive_data_access/zstd.cpython-313-darwin.so
hive_data_access/__init__.py
hive_data_access/converter.cpython-313-darwin.so
hive_data_access/common.cpython-313-darwin.so
hive_data_access/qual.cpython-313-darwin.so
hive_data_access/access.cpython-313-darwin.so
hive_data_access/quan.cpython-313-darwin.so
hive_data_access/exception.cpython-313-darwin.so
hive_data_access-0.17.0.dist-info/licenses/LICENSE
hive_data_access-0.17.0.dist-info/licenses/THIRD_PARTY_LICENSES.txt
hive_data_access-0.17.0.dist-info/licenses/NOTICE
hive_data_access-0.17.0.dist-info/WHEEL
hive_data_access-0.17.0.dist-info/top_level.txt
hive_data_access-0.17.0.dist-info/METADATA
hive_data_access-0.17.0.dist-info/RECORD
