Metadata-Version: 2.4
Name: hive-data-access
Version: 0.17.0
Summary: Programmatic access to Hive-format mass spectrometry data (.mzB/.hmD) in Python.
Author-email: "Reifycs Inc." <support@reifycs.com>
License-Expression: LicenseRef-Proprietary
Project-URL: license, https://www.reifycs.com/legal/hive-data-access-api-pdl
Project-URL: homepage, https://www.reifycs.com/products/hive/
Classifier: Programming Language :: Python :: 3
Classifier: Programming Language :: Python :: 3.10
Classifier: Programming Language :: Python :: 3.11
Classifier: Programming Language :: Python :: 3.12
Classifier: Programming Language :: Python :: 3.13
Classifier: Programming Language :: Python :: 3.14
Classifier: Operating System :: Microsoft :: Windows
Classifier: Operating System :: POSIX :: Linux
Classifier: Operating System :: MacOS
Requires-Python: <3.15,>=3.10
License-File: LICENSE
License-File: NOTICE
License-File: THIRD_PARTY_LICENSES.txt
Requires-Dist: python-dateutil>=2.8.2
Dynamic: license-file
